README.md
setup.py
nishanth/__init__.py
nishanth/client.py
nishanth.egg-info/PKG-INFO
nishanth.egg-info/SOURCES.txt
nishanth.egg-info/dependency_links.txt
nishanth.egg-info/not-zip-safe
nishanth.egg-info/requires.txt
nishanth.egg-info/top_level.txt