Metadata-Version: 2.1
Name: nishanth
Version: 1.4
Summary: Tribute to Nishanth
Home-page: UNKNOWN
Author: Vishnu Varthan Rao
Author-email: vishnulatha006@gmail.com
License: MIT License
Keywords: nishanth
Platform: UNKNOWN
Classifier: Intended Audience :: Developers
Classifier: License :: OSI Approved :: MIT License
Classifier: Programming Language :: Python :: 2
Classifier: Programming Language :: Python :: 2.6
Classifier: Programming Language :: Python :: 2.7
Classifier: Programming Language :: Python :: 3
Classifier: Programming Language :: Python :: 3.3
Classifier: Operating System :: OS Independent
Classifier: Topic :: Software Development :: Libraries
Classifier: Topic :: Utilities
